caux8_moodle_parser/__init__.py
caux8_moodle_parser/export.py
caux8_moodle_parser/question.py
caux8_moodle_parser/util.py
caux8_moodle_parser/ext_fmt/__init__.py
caux8_moodle_parser/ext_fmt/fps_xml.py
caux8_moodle_parser/ext_fmt/ybt.py
tests/__init__.py
tests/test_export.py
tests/test_fps.py
caux8_moodle_parser-1.0.0.dist-info/LICENSE
caux8_moodle_parser-1.0.0.dist-info/METADATA
caux8_moodle_parser-1.0.0.dist-info/WHEEL
caux8_moodle_parser-1.0.0.dist-info/top_level.txt
caux8_moodle_parser-1.0.0.dist-info/RECORD
