Metadata-Version: 2.2
Name: caux8_moodle_parser
Version: 1.0.0
Summary: Parser for converting a moodle-question-like python object to moodle xml format.
Home-page: https://github.com/YuZiOuO/CAUX8-Parser
Author: YuZiOuO & zxy-daiz
Author-email: cyz050312@gmail.com
Classifier: Programming Language :: Python :: 3
Classifier: License :: OSI Approved :: MIT License
Classifier: Operating System :: OS Independent
Requires-Python: >=3.10
License-File: LICENSE
Dynamic: author
Dynamic: author-email
Dynamic: classifier
Dynamic: description
Dynamic: description-content-type
Dynamic: home-page
Dynamic: requires-python
Dynamic: summary
